[
    {
        "domain": ".instagram.com",
        "expiry": 1781146689,
        "httpOnly": false,
        "name": "ig_nrcb",
        "path": "/",
        "sameSite": "Lax",
        "secure": true,
        "value": "1"
    },
    {
        "domain": ".instagram.com",
        "expiry": 1784170681,
        "httpOnly": false,
        "name": "mid",
        "path": "/",
        "sameSite": "Lax",
        "secure": true,
        "value": "aEjwvAALAAFg_Yq1Cj0zDSc3w83x"
    },
    {
        "domain": ".instagram.com",
        "expiry": 1750215489,
        "httpOnly": false,
        "name": "wd",
        "path": "/",
        "sameSite": "Lax",
        "secure": true,
        "value": "1904x985"
    },
    {
        "domain": ".instagram.com",
        "expiry": 1784170680,
        "httpOnly": true,
        "name": "ps_n",
        "path": "/",
        "sameSite": "None",
        "secure": true,
        "value": "1"
    },
    {
        "domain": ".instagram.com",
        "expiry": 1784170680,
        "httpOnly": true,
        "name": "ps_l",
        "path": "/",
        "sameSite": "Lax",
        "secure": true,
        "value": "1"
    },
    {
        "domain": ".instagram.com",
        "expiry": 1781146680,
        "httpOnly": true,
        "name": "ig_did",
        "path": "/",
        "sameSite": "None",
        "secure": true,
        "value": "26B700C2-B173-4C96-B2B7-91F14D0E7038"
    },
    {
        "domain": ".instagram.com",
        "expiry": 1784170680,
        "httpOnly": true,
        "name": "datr",
        "path": "/",
        "sameSite": "None",
        "secure": true,
        "value": "vPBIaJxLRJYJBw1OSadjMV4M"
    },
    {
        "domain": ".instagram.com",
        "expiry": 1784170699,
        "httpOnly": false,
        "name": "csrftoken",
        "path": "/",
        "sameSite": "Lax",
        "secure": true,
        "value": "bmwU9g4Sak9wWfvyRnVv2H"
    }
]